EitaaSender/__init__.py
eitaasender-1.0.0.dist-info/LICENSE
eitaasender-1.0.0.dist-info/METADATA
eitaasender-1.0.0.dist-info/WHEEL
eitaasender-1.0.0.dist-info/top_level.txt
eitaasender-1.0.0.dist-info/RECORD
